mongoslabs/__init__.py
mongoslabs/gencoords.py
mongoslabs/mongoloader.py
mongoslabs-0.0.2.dist-info/LICENSE
mongoslabs-0.0.2.dist-info/METADATA
mongoslabs-0.0.2.dist-info/WHEEL
mongoslabs-0.0.2.dist-info/top_level.txt
mongoslabs-0.0.2.dist-info/RECORD
