Metadata-Version: 2.1
Name: mongoslabs
Version: 0.0.2
Summary: Dataloader that serves MRI images from a mongodb
Home-page: https://github.com/neuroneural/mongoslabs
Author: Sergey Plis
Author-email: s.m.plis@gmail.com
License: MIT
License-File: LICENSE
Requires-Dist: numpy
Requires-Dist: scipy (>=1.7)
Requires-Dist: pymongo (>=4.0)
Requires-Dist: torch
